facteur/__init__.py
facteur/api.py
facteur-0.1.1.dist-info/METADATA
facteur-0.1.1.dist-info/WHEEL
facteur-0.1.1.dist-info/top_level.txt
facteur-0.1.1.dist-info/RECORD
