Metadata-Version: 2.1
Name: facteur
Version: 0.1.1
Summary: A simple Python package to send emails with Facteur.
Author: Alexis Bouchez
Author-email: contact@alexisbouchez.com
Classifier: Development Status :: 4 - Beta
Classifier: Intended Audience :: Developers
Classifier: License :: OSI Approved :: MIT License
Classifier: Operating System :: OS Independent
Classifier: Programming Language :: Python :: 3.7
Classifier: Programming Language :: Python :: 3.8
Classifier: Programming Language :: Python :: 3.9
Classifier: Programming Language :: Python :: 3.10
